IES_SCAN_API-1.1.12.dist-info/DESCRIPTION.rst
IES_SCAN_API-1.1.12.dist-info/METADATA
IES_SCAN_API-1.1.12.dist-info/RECORD
IES_SCAN_API-1.1.12.dist-info/WHEEL
IES_SCAN_API-1.1.12.dist-info/metadata.json
IES_SCAN_API-1.1.12.dist-info/top_level.txt
Scripts/__init__.py
Scripts/pkginfo-script.py
