Metadata-Version: 2.0
Name: IES-SCAN-API
Version: 1.1.12
Summary: Module containing the IES SCAN API.
Home-page: http://.scan.iesve.com
Author: Integrated Environmental Solutions
Author-email: dillan.mann@iesve.com
License: UNKNOWN
